Metadata-Version: 2.1
Name: RWWW_S
Version: 1.0.0
Summary: A removal tool for removing www and https://www. from dictionary's
Home-page: https://github.com/IEYT/RW-s
Author: Manveer Singh
Author-email: manveer1113@outlook.com
License: MIT
Keywords: RemoveWWW
Classifier: Development Status :: 5 - Production/Stable
Classifier: Intended Audience :: Developers
Classifier: Operating System :: Microsoft :: Windows :: Windows 11
Classifier: License :: OSI Approved :: MIT License
Classifier: Programming Language :: Python :: 3.12
License-File: LICENCE
